bounce_ws/__init__.py
bounce_ws/websocket_api.py
bounce_ws/handlers/__init__.py
bounce_ws/handlers/abstract_handler.py
bounce_ws/handlers/handler_orchestrator.py
bounce_ws/senders/__init__.py
bounce_ws/senders/abstract_sender.py
bounce_ws/senders/abstract_timed_sender.py
bounce_ws/senders/sender_orchestrator.py
bounce_ws-0.9.9.dist-info/LICENSE
bounce_ws-0.9.9.dist-info/METADATA
bounce_ws-0.9.9.dist-info/WHEEL
bounce_ws-0.9.9.dist-info/top_level.txt
bounce_ws-0.9.9.dist-info/RECORD
