Metadata-Version: 2.2
Name: bounce_ws
Version: 0.9.9
Summary: A simple framework for websocket event-based messaging using flask websockets under the hood
Home-page: https://github.com/Allorak/bounce-ws
Author: Mike Moiseev
Author-email: mvmoiseev@miem.hse.ru
Classifier: Programming Language :: Python :: 3
Classifier: License :: OSI Approved :: MIT License
Classifier: Operating System :: OS Independent
Classifier: Development Status :: 4 - Beta
Classifier: Framework :: FastAPI
Classifier: Natural Language :: English
Requires-Python: >=3.8
License-File: LICENSE
Requires-Dist: uvicorn[standard]
Requires-Dist: fastapi
Requires-Dist: loguru
Dynamic: author
Dynamic: author-email
Dynamic: classifier
Dynamic: description
Dynamic: description-content-type
Dynamic: home-page
Dynamic: requires-dist
Dynamic: requires-python
Dynamic: summary
